genbase/__init__.py
genbase/base_agent.py
genbase/types.py
genbase_client-0.1.8.dist-info/METADATA
genbase_client-0.1.8.dist-info/WHEEL
genbase_client-0.1.8.dist-info/entry_points.txt
genbase_client-0.1.8.dist-info/licenses/LICENSE
genbase_client-0.1.8.dist-info/RECORD
