Metadata-Version: 2.1
Name: genbase-client
Version: 0.1.8
Summary: RPyC client library for building Genbase agents.
Author-Email: Genbase <utkarshkanwat@email.com>
License: 
Classifier: License :: OSI Approved :: MIT License
Classifier: Programming Language :: Python :: 3
Classifier: Programming Language :: Python :: 3.9
Classifier: Programming Language :: Python :: 3.10
Classifier: Programming Language :: Python :: 3.11
Classifier: Operating System :: OS Independent
Classifier: Intended Audience :: Developers
Classifier: Topic :: Software Development :: Libraries :: Application Frameworks
Project-URL: Homepage, https://github.com/genbase-project/genbase
Requires-Python: >=3.9
Requires-Dist: rpyc>=6.0.1
Requires-Dist: pydantic>=2.0.0
Requires-Dist: loguru>=0.7.0
Requires-Dist: litellm>=1.35.0
Requires-Dist: dataclasses-json>=0.6.0
